fpl_extract_xml/__init__.py
fpl_extract_xml/__main__.py
fprime_fpl_extract_xml-1.0.3.dist-info/METADATA
fprime_fpl_extract_xml-1.0.3.dist-info/WHEEL
fprime_fpl_extract_xml-1.0.3.dist-info/entry_points.txt
fprime_fpl_extract_xml-1.0.3.dist-info/top_level.txt
fprime_fpl_extract_xml-1.0.3.dist-info/RECORD
